{
    "21779": ["League of Legends", "lol", "리그오브레전드", "롤"],
    "33214": ["Fortnite", "포트나이트", "포나"],
    "32399": ["Counter-Strike: Global Offensive", "카스", "카운터스트라이크"],
    "509658": ["Just Chatting", "채팅", "챗"],
    "489405": ["DragonBall Z: Dokkan Battle", "드래곤볼Z 폭렬격전"],
    "492934": ["Resident Evil 7 biohazard", "바이오하자드7", "바하7", "레지던트이블7"],
    "29595": ["Dota 2", "도타2"],
    "488552": ["Overwatch", "오버워치", "오버와치"],
    "506103": ["FIFA19", "피파19", "축구"],
    "512804": ["FIFA20", "피파20", "축구"],
    "18122": ["World of Warcraft", "와우", "월드오브워크래프트", "wow"],
    "32982": ["Grand Theft Auto V", "그타5", "지티에이5", "GTA5"],
    "493057": ["pubg", "PLAYERUNKNOWN\"S BATTLEGROUNDS", "베틀그라운드", "배틀그라운드", "배그", "베그"],
    "505884": ["pubg mobile", "BATTLEGROUNDS mobile", "베틀그라운드모바일", "배틀그라운드모바일", "모바일배그", "모바일베그","배그모바일", "베그모바일"],
    "27471": ["Minecraft", "마인크래프트", "마크"],
    "138585": ["Hearthstone", "하스스톤"],
    "460630": ["Tom Clancy\"s Rainbow Six: Siege", "레인보우식스 시즈"],
    "497057": ["Destiny 2", "데스티니2"],
    "11989": ["StarCraft", "스타크래프트"],
    "490422": ["StarCraft II", "StarCraft 2", "스타크래프트2", "스타2"],
    "29433": ["Dark Souls", "다크소울"],
    "489170": ["Dark Souls II", "Dark Souls 2", "다크소울2"],
    "490292": ["Dark Souls III", "Dark Souls 3", "다크소울3"],
    "506383": ["nba 2k19", "nba 19", "농구"],
    "513319": ["nba 2k20", "nba 20", "농구"],
    "5492": ["Diablo", "디아블로"],
    "14304": ["Diablo II: Lord of Destruction", "디아블로2", "디아2"],
    "313558": ["Diablo III: Reaper of Souls", "디아블로3", "디아3"],
    "497467": ["Monster Hunter World", "몬헌", "몬스터헌터월드"],
    "32959": ["Heroes of the Storm", "히오스", "히어로즈오브스톤"],
    "24241": ["FINAL FANTASY XIV Online", "FINAL FANTASY Online", "파판14 온라인", "파이널판타지14 온라인", "파판 온라인", "파이널판타지 온라인" ],
    "11988": ["Final Fantasy VII", "Final Fantasy 7", "파판7", "파이널판타지7"],
    "504199": ["Battlefield V", "배틀필드5", "배필5"],
    "2692": ["Super Mario 64", "슈퍼 마리오 64"],
    "461067": ["Tekken 7", "철권7"],
    "488615": ["Street Fighter V", "스트리트파이터5", "스파5"],
    "369252": ["The Sims 4", "심즈4"],
    "511748": ["Auto Chess", "오토체스" ],
    "509659": ["asmr"],
    "513143": ["Teamfight Tactics", "팀파이트", "롤체", "롤토체스"],
    "511224": ["Apex Legends", "아펙스레전드"],
    "494929": ["Lineage 2", "리니지2" ],
    "66170": ["warframe", "워프레임"],
    "510578": ["Mortal Kombat 11", "모탈컴뱃11"],
    "32345": ["Borderlands 2", "보더랜드2"],
    "491318": ["Borderlands 3", "보더랜드3"],
    "19976": ["MapleStory", "메이플스토리"],
    "499003": ["vrchat"],
    "509660": ["art", "아트", "그림"],
    "488190": ["Poker", "포커", "카드"],
    "66082": ["Games + Demos", "게임데모", "데모게임"],
    "512693": ["Dota Underlords", "도타언더로드", "도타언더로즈"],
    "417752": ["Talk Shows & Podcasts", "토크쇼 팟캐스트"],
    "26936": ["Music & Performing Arts", "뮤직", "음악", "노래", "노래방"],
    "263490": ["rust", "러스트"],
    "511399": ["Super Mario Maker 2", "슈퍼 마리오 메이커2"],
    "509249": ["The Dark Pictures Anthology: Man of Medan", "다크 픽처스 앤솔로지"],
    "2748": ["Magic: The Gathering", "매직 더 게더링"],
    "489545": ["Ancestors: The Humankind Odyssey", "앤세스터"],
    "491487": ["Dead by Daylight", "데드 바이 데이라이트", "데바데"],
    "459931": ["Old School RuneScape", "올드스쿨 룬스케이프"],
    "2083": ["RuneScape", "룬스케이프"],
    "504462": ["Call of Duty: Black Ops 4", "콜오브듀티4", "블랙옵스4", "콜옵4"],
    "118200": ["Call of Duty: Ghosts", "콜오브듀티 고스트", "콜옵 고스트"],
    "512710": ["Call of Duty: Modern Warfare", "콜오브듀티 모던어페어", "콜옵 모던어페어"],
    "500188": ["Hunt: Showdown", "헌트 쇼다운"],
    "506462": ["Control", "컨트롤"],
    "504461": ["Super Smash Bros. Ultimate", "슈퍼 스매시브라더스 얼티밋", "대난투 얼티밋"],
    "16282": ["Super Smash Bros. Melee", "슈퍼 스매시브라더스 밀리", "대난투 밀리"],
    "30921": ["Rocket League", "로켓 리그"],
    "509066": ["Remnant: From the Ashes", "렘넌트 프롬 더 애쉬"],
    "512371": ["Madden NFL 20", "미식축구", "럭비"],
    "511353": ["Astral Chain", "애스트럴 체인"],
    "11557": ["The Legend of Zelda: Ocarina of Time", "젤다의 전설 시간의 오카리나"],
    "9435": ["The Legend of Zelda: A Link to the Past", "젤다의 전설 신들의 트라이포스"],
    "386821": ["Black Desert Online", "검은사막", "검사"],
    "32507": ["Smite", "스마이트"],
    "27284": ["retro", "레트로"],
    "29307": ["Path of Exile", "패스 오브 엑자일", "poe"],
    "509670": ["Science & Technology", "과학기술"],
    "489635": ["ark", "아크"],
    "498000": ["House Flipper", "하우스 플리퍼"],
    "458781": ["No Man\"s Sky", "노맨즈 스카이", "노맨 스카이"],
    "489794": ["Yu-Gi-Oh! Legacy of the Duelist", "유희왕 듀얼리스트"],
    "494508": ["Yu-Gi-Oh! Duel Links", "유희왕 듀얼링크"],
    "19357": ["Guild Wars 2", "길드워2"],
    "512925": ["Pokemon Masters", "포켓몬 마스터즈", "포켓몬스터 마스터즈"],
    "506237": ["Pokemon: Let\"s Go, Pikachu!/Eevee!", "포켓몬스터 레츠고", "포멧몬 레츠고"],
    "7528": ["Pokémon Gold/Silver", "포켓몬스터 골드 실버", "포멧몬 골드 실버"],
    "27546": ["World of Tanks", "월드오브탱크", "월오탱"],
    "491080": ["The Binding of Isaac: Afterbirth", "아이작"],
    "16480": ["Digimon World 2", "디지몬 월드2"],
    "506415": ["Sekiro: Shadows Die Twice", "세키로"],
    "23020": ["ROBLOX", "로블록스"],
    "65632": ["DayZ", "데이즈"],
    "495202": ["Fire Emblem: Three Houses", "파이어 엠블렘 풍화설월", "파엠 풍화설월"],
    "460090": ["Subnautica", "서브노티카"],
    "65654": ["The Elder Scrolls Online", "엘더스크롤 온라인"],
    "509481": ["Twitch Sings", "노래"],
    "510146": ["MLB The Show 19", "야구"],
    "497315": ["Pro Evolution Soccer 2018", "위닝일레븐18", "축구"],
    "493048": ["Fate/Grand Order", "페이트 그랜드 오더"],
    "459382": ["Gears of War 4", "기어즈오브워4"],
    "504954": ["Ring Of Elysium", "링 오브 엘리시움", "링오엘"],
    "504463": ["The Division 2", "디비전2"],
    "12924": ["Warcraft III: The Frozen Throne", "Warcraft3", "워3", "워크래프트3"],
    "512887": ["The Seven Deadly Sins", "7개의 대죄", "일곱개의 대죄"],
    "491334": ["Kartrider", "카트라이더"],
    "500014": ["Old School Musical", "올드스쿨 뮤지컬"],
    "490724": ["Phoenix Wright: Ace Attorney Trilogy", "역전재판123 나루호도 셀렉션", "역전재판 나루호도 셀렉션"],
    "33507": ["Phoenix Wright: Ace Attorney Trilogy HD", "역전재판123 나루호도 셀렉션 HD", "역전재판 나루호도 셀렉션 HD"],
    "17777": ["Phoenix Wright: Ace Attorney", "역전재판"],
    "12261": ["Phoenix Wright: Ace Attorney - Justice For All", "역전재판2"],
    "7232": ["Phoenix Wright: Ace Attorney - Trials and Tribulations", "역전재판3"],
    "502732": ["Free Fire: Battlegrounds", "프리 파이어"]
}
